analysis/__init__.py
analysis/transforms.py
analysis/utils.py
fantasy/__init__.py
fantasy/version.py
fantasy/analysis/__init__.py
fantasy/analysis/transforms.py
fantasy/analysis/utils.py
fantasy/tasks/__init__.py
fantasy/tasks/league.py
fantasy/tasks/players.py
fantasy/tasks/rosters.py
fantasy/tasks/teams.py
fantasy_analysis-0.0.3.data/scripts/write_all_statistics
tasks/__init__.py
tasks/league.py
tasks/players.py
tasks/rosters.py
tasks/teams.py
fantasy_analysis-0.0.3.dist-info/METADATA
fantasy_analysis-0.0.3.dist-info/WHEEL
fantasy_analysis-0.0.3.dist-info/top_level.txt
fantasy_analysis-0.0.3.dist-info/RECORD
