Metadata-Version: 2.1
Name: fantasy-analysis
Version: 0.0.3
Summary: Library for doing analysis on a fantasy basketball league
Home-page: https://github.com/dthiagarajan/fantasy_exploration
Author: Dilip Thiagarajan
Author-email: dthiagar@gmail.com
License: MIT
Platform: UNKNOWN
Classifier: Programming Language :: Python :: 3 :: Only
Classifier: Operating System :: OS Independent
Requires-Python: >=3.6
Requires-Dist: appdirs (==1.4.4)
Requires-Dist: appnope (==0.1.0)
Requires-Dist: astroid (==2.3.3)
Requires-Dist: async-generator (==1.10)
Requires-Dist: backcall (==0.2.0)
Requires-Dist: black (==20.8b1)
Requires-Dist: certifi (==2020.12.5)
Requires-Dist: cffi (==1.14.4)
Requires-Dist: chardet (==4.0.0)
Requires-Dist: click (==7.1.2)
Requires-Dist: cloudpickle (==1.6.0)
Requires-Dist: croniter (==0.3.37)
Requires-Dist: dask (==2021.2.0)
Requires-Dist: decorator (==4.4.2)
Requires-Dist: defusedxml (==0.6.0)
Requires-Dist: distributed (==2021.2.0)
Requires-Dist: docker (==4.4.4)
Requires-Dist: entrypoints (==0.3)
Requires-Dist: flake8 (==3.7.9)
Requires-Dist: HeapDict (==1.0.1)
Requires-Dist: idna (==2.10)
Requires-Dist: importlib-metadata (==3.10.0)
Requires-Dist: ipykernel (==5.3.4)
Requires-Dist: ipython (==7.19.0)
Requires-Dist: ipython-genutils (==0.2.0)
Requires-Dist: isort (==4.3.21)
Requires-Dist: jedi (==0.17.2)
Requires-Dist: jupyter (==1.0.0)
Requires-Dist: jupyter-client (==6.1.7)
Requires-Dist: jupyter-contrib-core (==0.3.3)
Requires-Dist: jupyter-contrib-nbextensions (==0.5.1)
Requires-Dist: jupyter-core (==4.7.0)
Requires-Dist: jupyter-highlight-selected-word (==0.2.0)
Requires-Dist: jupyter-latex-envs (==1.4.6)
Requires-Dist: jupyter-nbextensions-configurator (==0.4.1)
Requires-Dist: lazy-object-proxy (==1.4.3)
Requires-Dist: lxml (==4.6.2)
Requires-Dist: MarkupSafe (==1.1.1)
Requires-Dist: marshmallow (==3.10.0)
Requires-Dist: marshmallow-oneofschema (==2.1.0)
Requires-Dist: mccabe (==0.6.1)
Requires-Dist: mistune (==0.8.4)
Requires-Dist: msgpack (==1.0.2)
Requires-Dist: mypy-extensions (==0.4.3)
Requires-Dist: natsort (==7.1.1)
Requires-Dist: nest-asyncio (==1.5.1)
Requires-Dist: numpy (==1.20.0)
Requires-Dist: pandas (==1.2.1)
Requires-Dist: parso (==0.7.1)
Requires-Dist: pathspec (==0.8.1)
Requires-Dist: pendulum (==2.1.2)
Requires-Dist: pexpect (==4.8.0)
Requires-Dist: pickleshare (==0.7.5)
Requires-Dist: prefect (==0.14.11)
Requires-Dist: prompt-toolkit (==3.0.8)
Requires-Dist: psutil (==5.8.0)
Requires-Dist: ptyprocess (==0.6.0)
Requires-Dist: pycodestyle (==2.5.0)
Requires-Dist: pyflakes (==2.1.1)
Requires-Dist: Pygments (==2.7.2)
Requires-Dist: pylint (==2.4.4)
Requires-Dist: python-box (==5.3.0)
Requires-Dist: python-dateutil (==2.8.1)
Requires-Dist: python-slugify (==4.0.1)
Requires-Dist: pytz (==2021.1)
Requires-Dist: pytzdata (==2020.1)
Requires-Dist: PyYAML (==5.4.1)
Requires-Dist: pyzmq (==20.0.0)
Requires-Dist: qtconsole (==5.0.2)
Requires-Dist: QtPy (==1.9.0)
Requires-Dist: regex (==2020.11.13)
Requires-Dist: requests (==2.25.1)
Requires-Dist: six (==1.14.0)
Requires-Dist: sortedcontainers (==2.3.0)
Requires-Dist: tabulate (==0.8.9)
Requires-Dist: tblib (==1.7.0)
Requires-Dist: terminado (==0.9.2)
Requires-Dist: text-unidecode (==1.3)
Requires-Dist: toml (==0.10.2)
Requires-Dist: toolz (==0.11.1)
Requires-Dist: tornado (==6.1)
Requires-Dist: tqdm (==4.59.0)
Requires-Dist: traitlets (==5.0.5)
Requires-Dist: typed-ast (==1.4.1)
Requires-Dist: typing-extensions (==3.7.4.3)
Requires-Dist: urllib3 (==1.26.3)
Requires-Dist: wcwidth (==0.2.5)
Requires-Dist: webencodings (==0.5.1)
Requires-Dist: websocket-client (==0.58.0)
Requires-Dist: widgetsnbextension (==3.5.1)
Requires-Dist: wrapt (==1.11.2)
Requires-Dist: zict (==2.0.0)
